pyspell/__init__.py
pyspell/spellcheck.py
pyspell-0.0.6.dist-info/METADATA
pyspell-0.0.6.dist-info/WHEEL
pyspell-0.0.6.dist-info/top_level.txt
pyspell-0.0.6.dist-info/RECORD
