Metadata-Version: 2.1
Name: pyspell
Version: 0.0.6
Summary: A simple spelling tool
Author: made-up
Project-URL: Homepage, https://github.com/vertmit/pyspell/tree/main/0.0.6
Project-URL: Bug Tracker, https://github.com/vertmit/pyspell/tree/main/issues
Classifier: Programming Language :: Python :: 3
Classifier: License :: OSI Approved :: MIT License
Classifier: Operating System :: OS Independent
Requires-Python: >=2.7
